{
    "ALU_test": [
        "ALU_test",
        "WNjR5",
        "module",
        1
    ],
    "XMC": [
        "XMC",
        "DJ6Ed",
        "module",
        2
    ],
    "XMD": [
        "XMD",
        "ZnePa",
        "module",
        3
    ],
    "YA2GSC": [
        "YA2GSC",
        "V9i98",
        "module",
        4
    ],
    "YA2GSD": [
        "YA2GSD",
        "pRkTU",
        "module",
        5
    ],
    "ZMA2GSC": [
        "ZMA2GSC",
        "x94rp",
        "module",
        6
    ],
    "ZMA2GSD": [
        "ZMA2GSD",
        "uF3kG",
        "module",
        7
    ],
    "dffrb_pri": [
        "dffrb_pri",
        "vUYHx",
        "module",
        8
    ],
    "dffsb_pri": [
        "dffsb_pri",
        "dEgCG",
        "module",
        9
    ],
    "pulldown_IO": [
        "pulldown_IO",
        "LHIGm",
        "module",
        10
    ],
    "pullup2_down_IO": [
        "pullup2_down_IO",
        "gddJt",
        "module",
        11
    ],
    "pullup_IO": [
        "pullup_IO",
        "Q2Z2h",
        "module",
        12
    ],
    "pullup_down_IO": [
        "pullup_down_IO",
        "QevUm",
        "module",
        13
    ],
    "pullup_down_IO_IEO": [
        "pullup_down_IO_IEO",
        "qEdvZ",
        "module",
        14
    ],
    "pullup_down_IO_PSCN": [
        "pullup_down_IO_PSCN",
        "vUqPt",
        "module",
        15
    ],
    "pullup_down_ene_IO": [
        "pullup_down_ene_IO",
        "J4ZAw",
        "module",
        16
    ],
    "pullup_down_keep_IO": [
        "pullup_down_keep_IO",
        "d8gdd",
        "module",
        17
    ],
    "pullup_down_keep_IO_03us": [
        "pullup_down_keep_IO_03us",
        "MSHGP",
        "module",
        18
    ],
    "pullup_down_keep_IO_IE": [
        "pullup_down_keep_IO_IE",
        "hGcMN",
        "module",
        19
    ],
    "pullup_down_keep_IO_IG": [
        "pullup_down_keep_IO_IG",
        "zRjsA",
        "module",
        20
    ],
    "pullup_inv_IO": [
        "pullup_inv_IO",
        "br5eJ",
        "module",
        21
    ],
    "AO222": [
        "AO222",
        "A27gf",
        "module",
        22
    ],
    "AOI22S": [
        "AOI22S",
        "wrIhr",
        "module",
        23
    ],
    "BUF1": [
        "BUF1",
        "VpcM6",
        "module",
        24
    ],
    "FA1S": [
        "FA1S",
        "ibUqY",
        "module",
        25
    ],
    "HA1": [
        "HA1",
        "b9apy",
        "module",
        26
    ],
    "INV12CK": [
        "INV12CK",
        "LMq1c",
        "module",
        27
    ],
    "INV1S": [
        "INV1S",
        "wqgB3",
        "module",
        28
    ],
    "MOAI1S": [
        "MOAI1S",
        "dKZ8Z",
        "module",
        29
    ],
    "ND2": [
        "ND2",
        "TxenJ",
        "module",
        30
    ],
    "ND3": [
        "ND3",
        "PbbMh",
        "module",
        31
    ],
    "NR2": [
        "NR2",
        "DUIFi",
        "module",
        32
    ],
    "OR3B2": [
        "OR3B2",
        "PsTg8",
        "module",
        33
    ],
    "QDFFRBN": [
        "QDFFRBN",
        "WAsjt",
        "module",
        34
    ],
    "TIE0": [
        "TIE0",
        "cDQY8",
        "module",
        35
    ],
    "TIE1": [
        "TIE1",
        "fUYbc",
        "module",
        36
    ],
    "XOR2HS": [
        "XOR2HS",
        "UifS7",
        "module",
        37
    ],
    "...MASTER...": [
        "SIM",
        "amcQw",
        "module",
        38
    ],
    "dffrsb_udp": [
        "dffrsb_udp",
        "qndjy",
        "udp",
        39
    ]
}